{
  "operations": {
    "AddPermission": {
      "TopicArn": {
        "completions": [
          {
            "parameters": {},
            "resourceIdentifier": "TopicArn",
            "resourceName": "Topic"
          }
        ]
      }
    },
    "CheckIfPhoneNumberIsOptedOut": {
      "phoneNumber": {
        "completions": [
          {
            "parameters": {},
            "resourceIdentifier": "phoneNumber",
            "resourceName": "PhoneNumbersOptedOut"
          }
        ]
      }
    },
    "ConfirmSubscription": {
      "TopicArn": {
        "completions": [
          {
            "parameters": {},
            "resourceIdentifier": "TopicArn",
            "resourceName": "Topic"
          }
        ]
      }
    },
    "DeletePlatformApplication": {
      "PlatformApplicationArn": {
        "completions": [
          {
            "parameters": {},
            "resourceIdentifier": "PlatformApplicationArn",
            "resourceName": "PlatformApplication"
          }
        ]
      }
    },
    "DeleteTopic": {
      "TopicArn": {
        "completions": [
          {
            "parameters": {},
            "resourceIdentifier": "TopicArn",
            "resourceName": "Topic"
          }
        ]
      }
    },
    "GetPlatformApplicationAttributes": {
      "PlatformApplicationArn": {
        "completions": [
          {
            "parameters": {},
            "resourceIdentifier": "PlatformApplicationArn",
            "resourceName": "PlatformApplication"
          }
        ]
      }
    },
    "GetSubscriptionAttributes": {
      "SubscriptionArn": {
        "completions": [
          {
            "parameters": {},
            "resourceIdentifier": "SubscriptionArn",
            "resourceName": "Subscription"
          }
        ]
      }
    },
    "GetTopicAttributes": {
      "TopicArn": {
        "completions": [
          {
            "parameters": {},
            "resourceIdentifier": "TopicArn",
            "resourceName": "Topic"
          }
        ]
      }
    },
    "ListEndpointsByPlatformApplication": {
      "PlatformApplicationArn": {
        "completions": [
          {
            "parameters": {},
            "resourceIdentifier": "PlatformApplicationArn",
            "resourceName": "PlatformApplication"
          }
        ]
      }
    },
    "ListSubscriptionsByTopic": {
      "TopicArn": {
        "completions": [
          {
            "parameters": {},
            "resourceIdentifier": "TopicArn",
            "resourceName": "Topic"
          }
        ]
      }
    },
    "OptInPhoneNumber": {
      "phoneNumber": {
        "completions": [
          {
            "parameters": {},
            "resourceIdentifier": "phoneNumber",
            "resourceName": "PhoneNumbersOptedOut"
          }
        ]
      }
    },
    "Publish": {
      "PhoneNumber": {
        "completions": [
          {
            "parameters": {},
            "resourceIdentifier": "phoneNumber",
            "resourceName": "PhoneNumbersOptedOut"
          }
        ]
      },
      "TopicArn": {
        "completions": [
          {
            "parameters": {},
            "resourceIdentifier": "TopicArn",
            "resourceName": "Topic"
          }
        ]
      }
    },
    "RemovePermission": {
      "TopicArn": {
        "completions": [
          {
            "parameters": {},
            "resourceIdentifier": "TopicArn",
            "resourceName": "Topic"
          }
        ]
      }
    },
    "SetEndpointAttributes": {
      "Attributes": {
        "completions": [
          {
            "parameters": {},
            "resourceIdentifier": "Attributes",
            "resourceName": "PlatformApplication"
          }
        ]
      }
    },
    "SetPlatformApplicationAttributes": {
      "Attributes": {
        "completions": [
          {
            "parameters": {},
            "resourceIdentifier": "Attributes",
            "resourceName": "PlatformApplication"
          }
        ]
      },
      "PlatformApplicationArn": {
        "completions": [
          {
            "parameters": {},
            "resourceIdentifier": "PlatformApplicationArn",
            "resourceName": "PlatformApplication"
          }
        ]
      }
    },
    "SetSubscriptionAttributes": {
      "SubscriptionArn": {
        "completions": [
          {
            "parameters": {},
            "resourceIdentifier": "SubscriptionArn",
            "resourceName": "Subscription"
          }
        ]
      }
    },
    "SetTopicAttributes": {
      "TopicArn": {
        "completions": [
          {
            "parameters": {},
            "resourceIdentifier": "TopicArn",
            "resourceName": "Topic"
          }
        ]
      }
    },
    "Subscribe": {
      "Attributes": {
        "completions": [
          {
            "parameters": {},
            "resourceIdentifier": "Attributes",
            "resourceName": "PlatformApplication"
          }
        ]
      },
      "Endpoint": {
        "completions": [
          {
            "parameters": {},
            "resourceIdentifier": "Endpoint",
            "resourceName": "Subscription"
          }
        ]
      },
      "Protocol": {
        "completions": [
          {
            "parameters": {},
            "resourceIdentifier": "Protocol",
            "resourceName": "Subscription"
          }
        ]
      },
      "TopicArn": {
        "completions": [
          {
            "parameters": {},
            "resourceIdentifier": "TopicArn",
            "resourceName": "Topic"
          }
        ]
      }
    },
    "Unsubscribe": {
      "SubscriptionArn": {
        "completions": [
          {
            "parameters": {},
            "resourceIdentifier": "SubscriptionArn",
            "resourceName": "Subscription"
          }
        ]
      }
    }
  },
  "resources": {
    "PhoneNumbersOptedOut": {
      "operation": "ListPhoneNumbersOptedOut",
      "resourceIdentifier": {
        "phoneNumber": "phoneNumbers[]"
      }
    },
    "PlatformApplication": {
      "operation": "ListPlatformApplications",
      "resourceIdentifier": {
        "Attributes": "PlatformApplications[].Attributes",
        "PlatformApplicationArn": "PlatformApplications[].PlatformApplicationArn"
      }
    },
    "Subscription": {
      "operation": "ListSubscriptions",
      "resourceIdentifier": {
        "Endpoint": "Subscriptions[].Endpoint",
        "Protocol": "Subscriptions[].Protocol",
        "SubscriptionArn": "Subscriptions[].SubscriptionArn"
      }
    },
    "Topic": {
      "operation": "ListTopics",
      "resourceIdentifier": {
        "TopicArn": "Topics[].TopicArn"
      }
    }
  },
  "version": "1.0"
}
